MANIFEST.in
README.md
pdf_tools.py
requirements.txt
setup.py
pdf_tools.egg-info/PKG-INFO
pdf_tools.egg-info/SOURCES.txt
pdf_tools.egg-info/dependency_links.txt
pdf_tools.egg-info/entry_points.txt
pdf_tools.egg-info/requires.txt
pdf_tools.egg-info/top_level.txt