Metadata-Version: 2.1
Name: pdf-tools
Version: 0.2.0
Summary: PDF tools, e.g. pdf2images, images2pdf, pdf2text, pdf2html, pdfmeta...
Home-page: UNKNOWN
Author: zencore-cn
Author-email: info@zencore.cn
License: MIT
Keywords: pdf-tools,images2pdf,pdf2images,pdf2html,pdf2text,pdfmeta
Platform: UNKNOWN
Classifier: Development Status :: 5 - Production/Stable
Classifier: Intended Audience :: Developers
Classifier: Topic :: Software Development :: Libraries :: Python Modules
Classifier: License :: OSI Approved :: MIT License
Classifier: Programming Language :: Python :: 3
Classifier: Programming Language :: Python :: 3 :: Only
Requires: click
Requires: pillow
Requires: PyMuPDF
